{
    "data":[

        {
            "id":1,
            "name":"A",
            "reviews":"4",
            "cost_for_one":"50",
            "categories":["breakfast","lunck","dinner"],
            "payment_methods":"all"
        },
        {
            "id":2,
            "name":"B",
            "reviews":"3",
            "cost_for_one":"50",
            "categories":["breakfast","lunck","dinner"],
            "payment_methods":"card"
        },
        {
            "id":3,
            "name":"c",
            "reviews":"2",
            "cost_for_one":"50",
            "categories":["breakfast","lunck","dinner"],
            "payment_methods": "cash"
        },
        {
            "id":4,
            "name":"d",
            "reviews":"4",
            "cost_for_one":"50",
            "categories":["breakfast","lunck","dinner"],
            "payment_methods":"card"
        },
        {
            "id":5,
            "name":"e",
            "reviews":"1",
            "cost_for_one":"50",
            "categories":["breakfast","lunck","dinner"],
            "payment_methods":"cash"
        },
        {
            "id":6,
            "name":"f",
            "reviews":"4",
            "cost_for_one":"50",
            "categories":["breakfast","lunck","dinner"],
            "payment_methods":"all"
        },
        {
            "id":7,
            "name":"g",
            "reviews":"5",
            "cost_for_one":"50",
            "categories":["breakfast","lunck","dinner"],
            "payment_methods":"all"
        },
        {
            "id":8,
            "name":"h",
            "reviews":"5",
            "cost_for_one":"50",
            "categories":["breakfast","lunck","dinner"],
            "payment_methods":"card"
        },
        {
            "id":9,
            "name":"i",
            "reviews":"5",
            "cost_for_one":"50",
            "categories":["breakfast","lunck","dinner"],
            "payment_methods":"cash"
        },
        {
            "id":10,
            "name":"J",
            "reviews":"4",
            "cost_for_one":"50",
            "categories":["breakfast","lunck","dinner"],
            "payment_methods":"card"
        }
    ]
}